torchph/__init__.py
torchph/nn/__init__.py
torchph/nn/slayer.py
torchph/pershom/__init__.py
torchph/pershom/pershom_backend.py
torchph-0.1.1.dist-info/LICENSE
torchph-0.1.1.dist-info/METADATA
torchph-0.1.1.dist-info/WHEEL
torchph-0.1.1.dist-info/top_level.txt
torchph-0.1.1.dist-info/RECORD
