Metadata-Version: 2.1
Name: torchph
Version: 0.1.1
Summary: torchph
Home-page: https://github.com/forkbabu/torchph
Author: Sayantan Das
Author-email: sayantandas30011998@gmail.com
License: UNKNOWN
Keywords: Persistent Homology
Platform: UNKNOWN
Classifier: Programming Language :: Python :: 3
Classifier: License :: OSI Approved :: MIT License
Classifier: Operating System :: OS Independent
Requires-Python: >=3.6
